numerai_compute_lite/__init__.py
numerai_compute_lite/main.py
numerai_compute_lite/model_pipeline.py
numerai_compute_lite/utils.py
numerai_compute_lite-0.0.2.dist-info/METADATA
numerai_compute_lite-0.0.2.dist-info/WHEEL
numerai_compute_lite-0.0.2.dist-info/top_level.txt
numerai_compute_lite-0.0.2.dist-info/RECORD
