Metadata-Version: 2.1
Name: numerai-compute-lite
Version: 0.0.2
Summary: Quick and easy way to deploy your Numerai models
Author-email: chanes <chris@numer.ai>
Project-URL: Homepage, https://github.com/numerai/compute_lite
Project-URL: Bug Tracker, https://github.com/numerai/compute_lite/issues
Classifier: Programming Language :: Python :: 3
Classifier: License :: OSI Approved :: MIT License
Classifier: Operating System :: OS Independent
Requires-Python: >=3.7
